HaMiP/HaMiP.py
HaMiP/__init__.py
HaMiP/R/chisq.R
HaMiP/R/gtest.R
HaMiP/R/nbtest.R
HaMiP/R/nbtest_sf.R
HaMiP/R/p.adj.R
HaMiP/R/ttest.R
HaMiP/perl/removeCommonRead.pl
HaMiP-0.0.3.2.dist-info/LICENSE
HaMiP-0.0.3.2.dist-info/METADATA
HaMiP-0.0.3.2.dist-info/WHEEL
HaMiP-0.0.3.2.dist-info/entry_points.txt
HaMiP-0.0.3.2.dist-info/top_level.txt
HaMiP-0.0.3.2.dist-info/RECORD
